{
  "meta": {
    "lastUpdated": "2026-06-22T10:39:36Z",
    "stage": "Group Stage",
    "matchday": 2,
    "eliminatedCount": 0,
    "recentResults": [
      {
        "home": "Mexico",
        "away": "South Africa",
        "homeScore": 2,
        "awayScore": 0,
        "round": "Group Stage"
      },
      {
        "home": "Korea Republic",
        "away": "Czechia",
        "homeScore": 2,
        "awayScore": 1,
        "round": "Group Stage"
      },
      {
        "home": "Canada",
        "away": "Bosnia-Herzegovina",
        "homeScore": 1,
        "awayScore": 1,
        "round": "Group Stage"
      },
      {
        "home": "USA",
        "away": "Paraguay",
        "homeScore": 4,
        "awayScore": 1,
        "round": "Group Stage"
      },
      {
        "home": "Qatar",
        "away": "Switzerland",
        "homeScore": 1,
        "awayScore": 1,
        "round": "Group Stage"
      },
      {
        "home": "Brazil",
        "away": "Morocco",
        "homeScore": 1,
        "awayScore": 1,
        "round": "Group Stage"
      },
      {
        "home": "Haiti",
        "away": "Scotland",
        "homeScore": 0,
        "awayScore": 1,
        "round": "Group Stage"
      },
      {
        "home": "Australia",
        "away": "TГјrkiye",
        "homeScore": 2,
        "awayScore": 0,
        "round": "Group Stage"
      },
      {
        "home": "Germany",
        "away": "CuraГ§ao",
        "homeScore": 7,
        "awayScore": 1,
        "round": "Group Stage"
      },
      {
        "home": "Netherlands",
        "away": "Japan",
        "homeScore": 2,
        "awayScore": 2,
        "round": "Group Stage"
      },
      {
        "home": "CГґte d'Ivoire",
        "away": "Ecuador",
        "homeScore": 1,
        "awayScore": 0,
        "round": "Group Stage"
      },
      {
        "home": "Sweden",
        "away": "Tunisia",
        "homeScore": 5,
        "awayScore": 1,
        "round": "Group Stage"
      },
      {
        "home": "Spain",
        "away": "Cabo Verde",
        "homeScore": 0,
        "awayScore": 0,
        "round": "Group Stage"
      },
      {
        "home": "Belgium",
        "away": "Egypt",
        "homeScore": 1,
        "awayScore": 1,
        "round": "Group Stage"
      },
      {
        "home": "Saudi Arabia",
        "away": "Uruguay",
        "homeScore": 1,
        "awayScore": 1,
        "round": "Group Stage"
      },
      {
        "home": "Iran",
        "away": "New Zealand",
        "homeScore": 2,
        "awayScore": 2,
        "round": "Group Stage"
      },
      {
        "home": "France",
        "away": "Senegal",
        "homeScore": 3,
        "awayScore": 1,
        "round": "Group Stage"
      },
      {
        "home": "Iraq",
        "away": "Norway",
        "homeScore": 1,
        "awayScore": 4,
        "round": "Group Stage"
      },
      {
        "home": "Argentina",
        "away": "Algeria",
        "homeScore": 3,
        "awayScore": 0,
        "round": "Group Stage"
      },
      {
        "home": "Austria",
        "away": "Jordan",
        "homeScore": 3,
        "awayScore": 1,
        "round": "Group Stage"
      },
      {
        "home": "Portugal",
        "away": "Congo DR",
        "homeScore": 1,
        "awayScore": 1,
        "round": "Group Stage"
      },
      {
        "home": "England",
        "away": "Croatia",
        "homeScore": 4,
        "awayScore": 2,
        "round": "Group Stage"
      },
      {
        "home": "Ghana",
        "away": "Panama",
        "homeScore": 1,
        "awayScore": 0,
        "round": "Group Stage"
      },
      {
        "home": "Uzbekistan",
        "away": "Colombia",
        "homeScore": 1,
        "awayScore": 3,
        "round": "Group Stage"
      },
      {
        "home": "Czechia",
        "away": "South Africa",
        "homeScore": 1,
        "awayScore": 1,
        "round": "Group Stage"
      },
      {
        "home": "Switzerland",
        "away": "Bosnia-Herzegovina",
        "homeScore": 4,
        "awayScore": 1,
        "round": "Group Stage"
      },
      {
        "home": "Canada",
        "away": "Qatar",
        "homeScore": 6,
        "awayScore": 0,
        "round": "Group Stage"
      },
      {
        "home": "Mexico",
        "away": "Korea Republic",
        "homeScore": 1,
        "awayScore": 0,
        "round": "Group Stage"
      },
      {
        "home": "USA",
        "away": "Australia",
        "homeScore": 2,
        "awayScore": 0,
        "round": "Group Stage"
      },
      {
        "home": "Scotland",
        "away": "Morocco",
        "homeScore": 0,
        "awayScore": 1,
        "round": "Group Stage"
      },
      {
        "home": "Brazil",
        "away": "Haiti",
        "homeScore": 3,
        "awayScore": 0,
        "round": "Group Stage"
      },
      {
        "home": "TГјrkiye",
        "away": "Paraguay",
        "homeScore": 0,
        "awayScore": 1,
        "round": "Group Stage"
      },
      {
        "home": "Netherlands",
        "away": "Sweden",
        "homeScore": 5,
        "awayScore": 1,
        "round": "Group Stage"
      },
      {
        "home": "Germany",
        "away": "CГґte d'Ivoire",
        "homeScore": 2,
        "awayScore": 1,
        "round": "Group Stage"
      },
      {
        "home": "Ecuador",
        "away": "CuraГ§ao",
        "homeScore": 0,
        "awayScore": 0,
        "round": "Group Stage"
      },
      {
        "home": "Tunisia",
        "away": "Japan",
        "homeScore": 0,
        "awayScore": 4,
        "round": "Group Stage"
      },
      {
        "home": "Spain",
        "away": "Saudi Arabia",
        "homeScore": 4,
        "awayScore": 0,
        "round": "Group Stage"
      },
      {
        "home": "Belgium",
        "away": "Iran",
        "homeScore": 0,
        "awayScore": 0,
        "round": "Group Stage"
      },
      {
        "home": "Uruguay",
        "away": "Cabo Verde",
        "homeScore": 2,
        "awayScore": 2,
        "round": "Group Stage"
      },
      {
        "home": "New Zealand",
        "away": "Egypt",
        "homeScore": 1,
        "awayScore": 3,
        "round": "Group Stage"
      }
    ]
  },
  "teams": {
    "Mexico": {
      "group": "A",
      "flag": "рџ‡Ірџ‡Ѕ",
      "status": "active",
      "pts": 0,
      "roundReached": null
    },
    "South Africa": {
      "group": "A",
      "flag": "рџ‡їрџ‡¦",
      "status": "active",
      "pts": 0,
      "roundReached": null
    },
    "Korea Republic": {
      "group": "A",
      "flag": "рџ‡°рџ‡·",
      "status": "active",
      "pts": 0,
      "roundReached": null
    },
    "Czechia": {
      "group": "A",
      "flag": "рџ‡Ёрџ‡ї",
      "status": "active",
      "pts": 0,
      "roundReached": null
    },
    "Canada": {
      "group": "B",
      "flag": "рџ‡Ёрџ‡¦",
      "status": "active",
      "pts": 0,
      "roundReached": null
    },
    "Bosnia & Herzegovina": {
      "group": "B",
      "flag": "рџ‡§рџ‡¦",
      "status": "active",
      "pts": 0,
      "roundReached": null
    },
    "Qatar": {
      "group": "B",
      "flag": "рџ‡¶рџ‡¦",
      "status": "active",
      "pts": 0,
      "roundReached": null
    },
    "Switzerland": {
      "group": "B",
      "flag": "рџ‡Ёрџ‡­",
      "status": "active",
      "pts": 0,
      "roundReached": null
    },
    "Brazil": {
      "group": "C",
      "flag": "рџ‡§рџ‡·",
      "status": "active",
      "pts": 0,
      "roundReached": null
    },
    "Morocco": {
      "group": "C",
      "flag": "рџ‡Ірџ‡¦",
      "status": "active",
      "pts": 0,
      "roundReached": null
    },
    "Haiti": {
      "group": "C",
      "flag": "рџ‡­рџ‡№",
      "status": "active",
      "pts": 0,
      "roundReached": null
    },
    "Scotland": {
      "group": "C",
      "flag": "рџЏґу Ѓ§у Ѓўу Ѓіу ЃЈу Ѓґу Ѓї",
      "status": "active",
      "pts": 0,
      "roundReached": null
    },
    "USA": {
      "group": "D",
      "flag": "рџ‡єрџ‡ё",
      "status": "active",
      "pts": 0,
      "roundReached": null
    },
    "Paraguay": {
      "group": "D",
      "flag": "рџ‡µрџ‡ѕ",
      "status": "active",
      "pts": 0,
      "roundReached": null
    },
    "Australia": {
      "group": "D",
      "flag": "рџ‡¦рџ‡є",
      "status": "active",
      "pts": 0,
      "roundReached": null
    },
    "TГјrkiye": {
      "group": "D",
      "flag": "рџ‡№рџ‡·",
      "status": "active",
      "pts": 0,
      "roundReached": null
    },
    "Germany": {
      "group": "E",
      "flag": "рџ‡©рџ‡Є",
      "status": "active",
      "pts": 0,
      "roundReached": null
    },
    "CuraГ§ao": {
      "group": "E",
      "flag": "рџ‡Ёрџ‡ј",
      "status": "active",
      "pts": 0,
      "roundReached": null
    },
    "CГґte d'Ivoire": {
      "group": "E",
      "flag": "рџ‡Ёрџ‡®",
      "status": "active",
      "pts": 0,
      "roundReached": null
    },
    "Ecuador": {
      "group": "E",
      "flag": "рџ‡Єрџ‡Ё",
      "status": "active",
      "pts": 0,
      "roundReached": null
    },
    "Netherlands": {
      "group": "F",
      "flag": "рџ‡ірџ‡±",
      "status": "active",
      "pts": 0,
      "roundReached": null
    },
    "Japan": {
      "group": "F",
      "flag": "рџ‡Їрџ‡µ",
      "status": "active",
      "pts": 0,
      "roundReached": null
    },
    "Sweden": {
      "group": "F",
      "flag": "рџ‡ёрџ‡Є",
      "status": "active",
      "pts": 0,
      "roundReached": null
    },
    "Tunisia": {
      "group": "F",
      "flag": "рџ‡№рџ‡і",
      "status": "active",
      "pts": 0,
      "roundReached": null
    },
    "Belgium": {
      "group": "G",
      "flag": "рџ‡§рџ‡Є",
      "status": "active",
      "pts": 0,
      "roundReached": null
    },
    "Egypt": {
      "group": "G",
      "flag": "рџ‡Єрџ‡¬",
      "status": "active",
      "pts": 0,
      "roundReached": null
    },
    "Iran": {
      "group": "G",
      "flag": "рџ‡®рџ‡·",
      "status": "active",
      "pts": 0,
      "roundReached": null
    },
    "New Zealand": {
      "group": "G",
      "flag": "рџ‡ірџ‡ї",
      "status": "active",
      "pts": 0,
      "roundReached": null
    },
    "Spain": {
      "group": "H",
      "flag": "рџ‡Єрџ‡ё",
      "status": "active",
      "pts": 0,
      "roundReached": null
    },
    "Cabo Verde": {
      "group": "H",
      "flag": "рџ‡Ёрџ‡»",
      "status": "active",
      "pts": 0,
      "roundReached": null
    },
    "Saudi Arabia": {
      "group": "H",
      "flag": "рџ‡ёрџ‡¦",
      "status": "active",
      "pts": 0,
      "roundReached": null
    },
    "Uruguay": {
      "group": "H",
      "flag": "рџ‡єрџ‡ѕ",
      "status": "active",
      "pts": 0,
      "roundReached": null
    },
    "France": {
      "group": "I",
      "flag": "рџ‡«рџ‡·",
      "status": "active",
      "pts": 0,
      "roundReached": null
    },
    "Senegal": {
      "group": "I",
      "flag": "рџ‡ёрџ‡і",
      "status": "active",
      "pts": 0,
      "roundReached": null
    },
    "Iraq": {
      "group": "I",
      "flag": "рџ‡®рџ‡¶",
      "status": "active",
      "pts": 0,
      "roundReached": null
    },
    "Norway": {
      "group": "I",
      "flag": "рџ‡ірџ‡ґ",
      "status": "active",
      "pts": 0,
      "roundReached": null
    },
    "Argentina": {
      "group": "J",
      "flag": "рџ‡¦рџ‡·",
      "status": "active",
      "pts": 0,
      "roundReached": null
    },
    "Algeria": {
      "group": "J",
      "flag": "рџ‡©рџ‡ї",
      "status": "active",
      "pts": 0,
      "roundReached": null
    },
    "Austria": {
      "group": "J",
      "flag": "рџ‡¦рџ‡№",
      "status": "active",
      "pts": 0,
      "roundReached": null
    },
    "Jordan": {
      "group": "J",
      "flag": "рџ‡Їрџ‡ґ",
      "status": "active",
      "pts": 0,
      "roundReached": null
    },
    "Portugal": {
      "group": "K",
      "flag": "рџ‡µрџ‡№",
      "status": "active",
      "pts": 0,
      "roundReached": null
    },
    "Congo DR": {
      "group": "K",
      "flag": "рџ‡Ёрџ‡©",
      "status": "active",
      "pts": 0,
      "roundReached": null
    },
    "Uzbekistan": {
      "group": "K",
      "flag": "рџ‡єрџ‡ї",
      "status": "active",
      "pts": 0,
      "roundReached": null
    },
    "Colombia": {
      "group": "K",
      "flag": "рџ‡Ёрџ‡ґ",
      "status": "active",
      "pts": 0,
      "roundReached": null
    },
    "England": {
      "group": "L",
      "flag": "рџЏґу Ѓ§у Ѓўу ЃҐу Ѓ®у Ѓ§у Ѓї",
      "status": "active",
      "pts": 0,
      "roundReached": null
    },
    "Croatia": {
      "group": "L",
      "flag": "рџ‡­рџ‡·",
      "status": "active",
      "pts": 0,
      "roundReached": null
    },
    "Ghana": {
      "group": "L",
      "flag": "рџ‡¬рџ‡­",
      "status": "active",
      "pts": 0,
      "roundReached": null
    },
    "Panama": {
      "group": "L",
      "flag": "рџ‡µрџ‡¦",
      "status": "active",
      "pts": 0,
      "roundReached": null
    }
  }
}